[{"word":"നാലാം","time":0.015},{"word":"രഹസ്യം.","time":0.457},{"word":"ദേവാലയത്തിൽ","time":1.147},{"word":"കാഴ്ചവയ്ക്കൽ.","time":1.829},{"word":"പരിശുദ്ധ","time":2.731},{"word":"ദൈവമാതാവ്","time":3.263},{"word":"തന്റെ","time":4.014},{"word":"ശുദ്ധീകരണത്തിന്റെ","time":4.274},{"word":"നാൾ","time":5.061},{"word":"വന്നപ്പോൾ","time":5.266},{"word":"ഈശോമിശിഹായെ","time":5.776},{"word":"ദേവാലയത്തിൽ","time":6.572},{"word":"കൊണ്ടുചെന്ന്","time":7.163},{"word":"ദൈവത്തിനു","time":7.628},{"word":"കാഴ്ചവച്ച്","time":8.108},{"word":"ശിമയോൻ","time":8.658},{"word":"എന്ന","time":9.069},{"word":"മഹാത്മാവിന്റെ","time":9.264},{"word":"കരങ്ങളിൽ","time":9.919},{"word":"ഏൽപ്പിച്ചു","time":10.37},{"word":"എന്ന്","time":10.835},{"word":"ധ്യാനിക്കുക.","time":10.995}]